{
  "id": "smp-7-ppkn",
  "tingkat": "SMP Kelas 7",
  "mapel": "PPKn",
  "tipe": "Latihan Soal",
  "soal": [
    {
      "id": "smp-7-ppkn-1",
      "teks": "Lembaga bentukan Jepang yang bertugas menyelidiki kesiapan kemerdekaan Indonesia adalah... (Latihan #1)",
      "opsi": {
        "A": "BPUPKI",
        "B": "PPKI",
        "C": "KNIP",
        "D": "DPR",
        "E": "MPR"
      },
      "kunci": "A",
      "pembahasan": "Jepang membentuk BPUPKI (Badan Penyelidik Usaha-usaha Persiapan Kemerdekaan Indonesia) atau Dokuritsu Junbi Cosakai untuk menyelidiki segala persiapan.",
      "trik": "Penyelidik = BPUPKI. Persiapan final = PPKI."
    },
    {
      "id": "smp-7-ppkn-2",
      "teks": "Tokoh yang mengusulkan rumusan dasar negara pada tanggal 1 Juni 1945 dan memberikan nama Pancasila adalah... (Latihan #2)",
      "opsi": {
        "A": "Bung Hatta",
        "B": "Ir. Soekarno",
        "C": "Muh. Yamin",
        "D": "Soepomo",
        "E": "A.A. Maramis"
      },
      "kunci": "B",
      "pembahasan": "Dalam sidang BPUPKI tanggal 1 Juni 1945, Ir. Soekarno menyampaikan usulan dasar negara dan memberinya nama Pancasila.",
      "trik": "Hari Lahir Pancasila (1 Juni) = Pidato Ir. Soekarno."
    },
    {
      "id": "smp-7-ppkn-3",
      "teks": "Panitia yang merumuskan Piagam Jakarta (Jakarta Charter) sebagai cikal bakal pembukaan UUD 1945 adalah... (Latihan #3)",
      "opsi": {
        "A": "Panitia Kecil",
        "B": "PPKI",
        "C": "Panitia Sembilan",
        "D": "BPUPKI",
        "E": "KNIP"
      },
      "kunci": "C",
      "pembahasan": "Panitia Sembilan yang dibentuk BPUPKI berhasil merumuskan naskah Mukadimah yang dikenal sebagai Piagam Jakarta pada 22 Juni 1945.",
      "trik": "Piagam Jakarta dihasilkan oleh 9 tokoh perumus (Panitia Sembilan)."
    },
    {
      "id": "smp-7-ppkn-4",
      "teks": "Aturan yang sumbernya berasal dari hati nurani manusia mengenai baik dan buruk suatu perbuatan disebut norma... (Latihan #4)",
      "opsi": {
        "A": "Agama",
        "B": "Kesopanan",
        "C": "Hukum",
        "D": "Kesusilaan",
        "E": "Adat"
      },
      "kunci": "D",
      "pembahasan": "Norma kesusilaan bersumber dari bisikan kalbu/hati nurani untuk menilai baik dan buruk (contoh: jujur, tidak menipu).",
      "trik": "Hati nurani = Kesusilaan."
    },
    {
      "id": "smp-7-ppkn-5",
      "teks": "Sanksi berupa pengucilan, dicemooh, atau tidak diikutsertakan dalam kegiatan masyarakat merupakan pelanggaran terhadap norma... (Latihan #5)",
      "opsi": {
        "A": "Hukum",
        "B": "Agama",
        "C": "Kesusilaan",
        "D": "Negara",
        "E": "Kesopanan dan adat"
      },
      "kunci": "E",
      "pembahasan": "Norma kesopanan (dan adat) adalah aturan pergaulan di masyarakat, sehingga pelanggarannya akan dikenai sanksi sosial seperti dikucilkan/dicemooh.",
      "trik": "Dihukum penjara = Hukum. Dosa = Agama. Dikucilkan = Kesopanan/Adat."
    },
    {
      "id": "smp-7-ppkn-6",
      "teks": "Sikap toleransi dalam kehidupan antarumat beragama di Indonesia bertujuan untuk... (Latihan #6)",
      "opsi": {
        "A": "Mewujudkan kerukunan dan kedamaian nasional",
        "B": "Mencapai satu ajaran agama",
        "C": "Menghindari hukuman pidana",
        "D": "Menyamakan keyakinan seluruh penduduk",
        "E": "Meningkatkan ibadah bersama antaragama"
      },
      "kunci": "A",
      "pembahasan": "Toleransi bertujuan menjalin kerukunan di tengah keragaman, menjaga kedamaian, bukan untuk menyamakan/menggabungkan keyakinan.",
      "trik": "Toleransi = rukun dengan saling membiarkan dan menghormati ibadah masing-masing."
    },
    {
      "id": "smp-7-ppkn-7",
      "teks": "Prinsip semboyan 'Bhinneka Tunggal Ika' bagi bangsa Indonesia adalah sebagai... (Latihan #7)",
      "opsi": {
        "A": "Alat perpecahan masyarakat",
        "B": "Pemersatu di tengah keberagaman suku, agama, dan budaya",
        "C": "Simbol dominasi mayoritas",
        "D": "Penanda bahwa Indonesia merupakan negara agama",
        "E": "Identitas bahwa suku tertentu lebih unggul"
      },
      "kunci": "B",
      "pembahasan": "Bhinneka Tunggal Ika artinya 'Berbeda-beda tetapi tetap satu jua', merupakan alat pemersatu bangsa yang majemuk.",
      "trik": "Bhinneka = Berbeda. Tunggal Ika = Satu Jua -> Pemersatu."
    },
    {
      "id": "smp-7-ppkn-8",
      "teks": "Sikap etnosentrisme dapat membahayakan NKRI karena... (Latihan #8)",
      "opsi": {
        "A": "Membuat kebudayaan luar mudah masuk",
        "B": "Memicu pertumbuhan ekonomi",
        "C": "Menganggap suku bangsa sendiri paling baik dan merendahkan suku lain",
        "D": "Dapat memperkuat dasar negara Pancasila",
        "E": "Menimbulkan sifat individualisme yang ekstrem"
      },
      "kunci": "C",
      "pembahasan": "Etnosentrisme adalah pandangan yang menganggap budayanya/sukunya lebih superior/baik daripada yang lain, sehingga memicu perpecahan.",
      "trik": "Etno = Suku/Budaya. Sentris = Berpusat (Merasa sukunya paling sentral/baik)."
    },
    {
      "id": "smp-7-ppkn-9",
      "teks": "Contoh pelaksanaan gotong royong yang merupakan wujud kerja sama di lingkungan sekolah adalah... (Latihan #9)",
      "opsi": {
        "A": "Menyontek saat ujian bersama-sama",
        "B": "Iuran memperbaiki jembatan desa",
        "C": "Salat jamaah di masjid komplek",
        "D": "Membersihkan kelas bersama regu piket",
        "E": "Memasak bersama keluarga di hari libur"
      },
      "kunci": "D",
      "pembahasan": "Lingkungan sekolah = kegiatan yang di area sekolah (pikét kelas, membersihkan taman baca, dll).",
      "trik": "Lihat konteks tempat: 'lingkungan sekolah' -> berkaitan dng kegiatan di sekolah."
    },
    {
      "id": "smp-7-ppkn-10",
      "teks": "Menolong korban bencana alam tanpa membedakan suku asalnya merupakan penerapan nilai Pancasila ke-... (Latihan #10)",
      "opsi": {
        "A": "SATU - Ketuhanan Yang Maha Esa",
        "B": "TIGA - Persatuan Indonesia",
        "C": "EMPAT - Kerakyatan yang Dipimpin... ",
        "D": "LIMA - Keadilan Sosial...",
        "E": "DUA - Kemanusiaan yang Adil dan Beradab"
      },
      "kunci": "E",
      "pembahasan": "Sikap saling peduli, menolong, menjunjung tinggi HAM, kemanusiaan masuk pada sila kedua (kemanusiaan yang beradab).",
      "trik": "Tolong-menolong/Donasi/Relawan = Sila 2."
    },
    {
      "id": "smp-7-ppkn-11",
      "teks": "Lembaga bentukan Jepang yang bertugas menyelidiki kesiapan kemerdekaan Indonesia adalah... (Latihan #11)",
      "opsi": {
        "A": "BPUPKI",
        "B": "PPKI",
        "C": "KNIP",
        "D": "DPR",
        "E": "MPR"
      },
      "kunci": "A",
      "pembahasan": "Jepang membentuk BPUPKI (Badan Penyelidik Usaha-usaha Persiapan Kemerdekaan Indonesia) atau Dokuritsu Junbi Cosakai untuk menyelidiki segala persiapan.",
      "trik": "Penyelidik = BPUPKI. Persiapan final = PPKI."
    },
    {
      "id": "smp-7-ppkn-12",
      "teks": "Tokoh yang mengusulkan rumusan dasar negara pada tanggal 1 Juni 1945 dan memberikan nama Pancasila adalah... (Latihan #12)",
      "opsi": {
        "A": "Bung Hatta",
        "B": "Ir. Soekarno",
        "C": "Muh. Yamin",
        "D": "Soepomo",
        "E": "A.A. Maramis"
      },
      "kunci": "B",
      "pembahasan": "Dalam sidang BPUPKI tanggal 1 Juni 1945, Ir. Soekarno menyampaikan usulan dasar negara dan memberinya nama Pancasila.",
      "trik": "Hari Lahir Pancasila (1 Juni) = Pidato Ir. Soekarno."
    },
    {
      "id": "smp-7-ppkn-13",
      "teks": "Panitia yang merumuskan Piagam Jakarta (Jakarta Charter) sebagai cikal bakal pembukaan UUD 1945 adalah... (Latihan #13)",
      "opsi": {
        "A": "Panitia Kecil",
        "B": "PPKI",
        "C": "Panitia Sembilan",
        "D": "BPUPKI",
        "E": "KNIP"
      },
      "kunci": "C",
      "pembahasan": "Panitia Sembilan yang dibentuk BPUPKI berhasil merumuskan naskah Mukadimah yang dikenal sebagai Piagam Jakarta pada 22 Juni 1945.",
      "trik": "Piagam Jakarta dihasilkan oleh 9 tokoh perumus (Panitia Sembilan)."
    },
    {
      "id": "smp-7-ppkn-14",
      "teks": "Aturan yang sumbernya berasal dari hati nurani manusia mengenai baik dan buruk suatu perbuatan disebut norma... (Latihan #14)",
      "opsi": {
        "A": "Agama",
        "B": "Kesopanan",
        "C": "Hukum",
        "D": "Kesusilaan",
        "E": "Adat"
      },
      "kunci": "D",
      "pembahasan": "Norma kesusilaan bersumber dari bisikan kalbu/hati nurani untuk menilai baik dan buruk (contoh: jujur, tidak menipu).",
      "trik": "Hati nurani = Kesusilaan."
    },
    {
      "id": "smp-7-ppkn-15",
      "teks": "Sanksi berupa pengucilan, dicemooh, atau tidak diikutsertakan dalam kegiatan masyarakat merupakan pelanggaran terhadap norma... (Latihan #15)",
      "opsi": {
        "A": "Hukum",
        "B": "Agama",
        "C": "Kesusilaan",
        "D": "Negara",
        "E": "Kesopanan dan adat"
      },
      "kunci": "E",
      "pembahasan": "Norma kesopanan (dan adat) adalah aturan pergaulan di masyarakat, sehingga pelanggarannya akan dikenai sanksi sosial seperti dikucilkan/dicemooh.",
      "trik": "Dihukum penjara = Hukum. Dosa = Agama. Dikucilkan = Kesopanan/Adat."
    },
    {
      "id": "smp-7-ppkn-16",
      "teks": "Sikap toleransi dalam kehidupan antarumat beragama di Indonesia bertujuan untuk... (Latihan #16)",
      "opsi": {
        "A": "Mewujudkan kerukunan dan kedamaian nasional",
        "B": "Mencapai satu ajaran agama",
        "C": "Menghindari hukuman pidana",
        "D": "Menyamakan keyakinan seluruh penduduk",
        "E": "Meningkatkan ibadah bersama antaragama"
      },
      "kunci": "A",
      "pembahasan": "Toleransi bertujuan menjalin kerukunan di tengah keragaman, menjaga kedamaian, bukan untuk menyamakan/menggabungkan keyakinan.",
      "trik": "Toleransi = rukun dengan saling membiarkan dan menghormati ibadah masing-masing."
    },
    {
      "id": "smp-7-ppkn-17",
      "teks": "Prinsip semboyan 'Bhinneka Tunggal Ika' bagi bangsa Indonesia adalah sebagai... (Latihan #17)",
      "opsi": {
        "A": "Alat perpecahan masyarakat",
        "B": "Pemersatu di tengah keberagaman suku, agama, dan budaya",
        "C": "Simbol dominasi mayoritas",
        "D": "Penanda bahwa Indonesia merupakan negara agama",
        "E": "Identitas bahwa suku tertentu lebih unggul"
      },
      "kunci": "B",
      "pembahasan": "Bhinneka Tunggal Ika artinya 'Berbeda-beda tetapi tetap satu jua', merupakan alat pemersatu bangsa yang majemuk.",
      "trik": "Bhinneka = Berbeda. Tunggal Ika = Satu Jua -> Pemersatu."
    },
    {
      "id": "smp-7-ppkn-18",
      "teks": "Sikap etnosentrisme dapat membahayakan NKRI karena... (Latihan #18)",
      "opsi": {
        "A": "Membuat kebudayaan luar mudah masuk",
        "B": "Memicu pertumbuhan ekonomi",
        "C": "Menganggap suku bangsa sendiri paling baik dan merendahkan suku lain",
        "D": "Dapat memperkuat dasar negara Pancasila",
        "E": "Menimbulkan sifat individualisme yang ekstrem"
      },
      "kunci": "C",
      "pembahasan": "Etnosentrisme adalah pandangan yang menganggap budayanya/sukunya lebih superior/baik daripada yang lain, sehingga memicu perpecahan.",
      "trik": "Etno = Suku/Budaya. Sentris = Berpusat (Merasa sukunya paling sentral/baik)."
    },
    {
      "id": "smp-7-ppkn-19",
      "teks": "Contoh pelaksanaan gotong royong yang merupakan wujud kerja sama di lingkungan sekolah adalah... (Latihan #19)",
      "opsi": {
        "A": "Menyontek saat ujian bersama-sama",
        "B": "Iuran memperbaiki jembatan desa",
        "C": "Salat jamaah di masjid komplek",
        "D": "Membersihkan kelas bersama regu piket",
        "E": "Memasak bersama keluarga di hari libur"
      },
      "kunci": "D",
      "pembahasan": "Lingkungan sekolah = kegiatan yang di area sekolah (pikét kelas, membersihkan taman baca, dll).",
      "trik": "Lihat konteks tempat: 'lingkungan sekolah' -> berkaitan dng kegiatan di sekolah."
    },
    {
      "id": "smp-7-ppkn-20",
      "teks": "Menolong korban bencana alam tanpa membedakan suku asalnya merupakan penerapan nilai Pancasila ke-... (Latihan #20)",
      "opsi": {
        "A": "SATU - Ketuhanan Yang Maha Esa",
        "B": "TIGA - Persatuan Indonesia",
        "C": "EMPAT - Kerakyatan yang Dipimpin... ",
        "D": "LIMA - Keadilan Sosial...",
        "E": "DUA - Kemanusiaan yang Adil dan Beradab"
      },
      "kunci": "E",
      "pembahasan": "Sikap saling peduli, menolong, menjunjung tinggi HAM, kemanusiaan masuk pada sila kedua (kemanusiaan yang beradab).",
      "trik": "Tolong-menolong/Donasi/Relawan = Sila 2."
    },
    {
      "id": "smp-7-ppkn-21",
      "teks": "Lembaga bentukan Jepang yang bertugas menyelidiki kesiapan kemerdekaan Indonesia adalah... (Latihan #21)",
      "opsi": {
        "A": "BPUPKI",
        "B": "PPKI",
        "C": "KNIP",
        "D": "DPR",
        "E": "MPR"
      },
      "kunci": "A",
      "pembahasan": "Jepang membentuk BPUPKI (Badan Penyelidik Usaha-usaha Persiapan Kemerdekaan Indonesia) atau Dokuritsu Junbi Cosakai untuk menyelidiki segala persiapan.",
      "trik": "Penyelidik = BPUPKI. Persiapan final = PPKI."
    },
    {
      "id": "smp-7-ppkn-22",
      "teks": "Tokoh yang mengusulkan rumusan dasar negara pada tanggal 1 Juni 1945 dan memberikan nama Pancasila adalah... (Latihan #22)",
      "opsi": {
        "A": "Bung Hatta",
        "B": "Ir. Soekarno",
        "C": "Muh. Yamin",
        "D": "Soepomo",
        "E": "A.A. Maramis"
      },
      "kunci": "B",
      "pembahasan": "Dalam sidang BPUPKI tanggal 1 Juni 1945, Ir. Soekarno menyampaikan usulan dasar negara dan memberinya nama Pancasila.",
      "trik": "Hari Lahir Pancasila (1 Juni) = Pidato Ir. Soekarno."
    },
    {
      "id": "smp-7-ppkn-23",
      "teks": "Panitia yang merumuskan Piagam Jakarta (Jakarta Charter) sebagai cikal bakal pembukaan UUD 1945 adalah... (Latihan #23)",
      "opsi": {
        "A": "Panitia Kecil",
        "B": "PPKI",
        "C": "Panitia Sembilan",
        "D": "BPUPKI",
        "E": "KNIP"
      },
      "kunci": "C",
      "pembahasan": "Panitia Sembilan yang dibentuk BPUPKI berhasil merumuskan naskah Mukadimah yang dikenal sebagai Piagam Jakarta pada 22 Juni 1945.",
      "trik": "Piagam Jakarta dihasilkan oleh 9 tokoh perumus (Panitia Sembilan)."
    },
    {
      "id": "smp-7-ppkn-24",
      "teks": "Aturan yang sumbernya berasal dari hati nurani manusia mengenai baik dan buruk suatu perbuatan disebut norma... (Latihan #24)",
      "opsi": {
        "A": "Agama",
        "B": "Kesopanan",
        "C": "Hukum",
        "D": "Kesusilaan",
        "E": "Adat"
      },
      "kunci": "D",
      "pembahasan": "Norma kesusilaan bersumber dari bisikan kalbu/hati nurani untuk menilai baik dan buruk (contoh: jujur, tidak menipu).",
      "trik": "Hati nurani = Kesusilaan."
    },
    {
      "id": "smp-7-ppkn-25",
      "teks": "Sanksi berupa pengucilan, dicemooh, atau tidak diikutsertakan dalam kegiatan masyarakat merupakan pelanggaran terhadap norma... (Latihan #25)",
      "opsi": {
        "A": "Hukum",
        "B": "Agama",
        "C": "Kesusilaan",
        "D": "Negara",
        "E": "Kesopanan dan adat"
      },
      "kunci": "E",
      "pembahasan": "Norma kesopanan (dan adat) adalah aturan pergaulan di masyarakat, sehingga pelanggarannya akan dikenai sanksi sosial seperti dikucilkan/dicemooh.",
      "trik": "Dihukum penjara = Hukum. Dosa = Agama. Dikucilkan = Kesopanan/Adat."
    },
    {
      "id": "smp-7-ppkn-26",
      "teks": "Sikap toleransi dalam kehidupan antarumat beragama di Indonesia bertujuan untuk... (Latihan #26)",
      "opsi": {
        "A": "Mewujudkan kerukunan dan kedamaian nasional",
        "B": "Mencapai satu ajaran agama",
        "C": "Menghindari hukuman pidana",
        "D": "Menyamakan keyakinan seluruh penduduk",
        "E": "Meningkatkan ibadah bersama antaragama"
      },
      "kunci": "A",
      "pembahasan": "Toleransi bertujuan menjalin kerukunan di tengah keragaman, menjaga kedamaian, bukan untuk menyamakan/menggabungkan keyakinan.",
      "trik": "Toleransi = rukun dengan saling membiarkan dan menghormati ibadah masing-masing."
    },
    {
      "id": "smp-7-ppkn-27",
      "teks": "Prinsip semboyan 'Bhinneka Tunggal Ika' bagi bangsa Indonesia adalah sebagai... (Latihan #27)",
      "opsi": {
        "A": "Alat perpecahan masyarakat",
        "B": "Pemersatu di tengah keberagaman suku, agama, dan budaya",
        "C": "Simbol dominasi mayoritas",
        "D": "Penanda bahwa Indonesia merupakan negara agama",
        "E": "Identitas bahwa suku tertentu lebih unggul"
      },
      "kunci": "B",
      "pembahasan": "Bhinneka Tunggal Ika artinya 'Berbeda-beda tetapi tetap satu jua', merupakan alat pemersatu bangsa yang majemuk.",
      "trik": "Bhinneka = Berbeda. Tunggal Ika = Satu Jua -> Pemersatu."
    },
    {
      "id": "smp-7-ppkn-28",
      "teks": "Sikap etnosentrisme dapat membahayakan NKRI karena... (Latihan #28)",
      "opsi": {
        "A": "Membuat kebudayaan luar mudah masuk",
        "B": "Memicu pertumbuhan ekonomi",
        "C": "Menganggap suku bangsa sendiri paling baik dan merendahkan suku lain",
        "D": "Dapat memperkuat dasar negara Pancasila",
        "E": "Menimbulkan sifat individualisme yang ekstrem"
      },
      "kunci": "C",
      "pembahasan": "Etnosentrisme adalah pandangan yang menganggap budayanya/sukunya lebih superior/baik daripada yang lain, sehingga memicu perpecahan.",
      "trik": "Etno = Suku/Budaya. Sentris = Berpusat (Merasa sukunya paling sentral/baik)."
    },
    {
      "id": "smp-7-ppkn-29",
      "teks": "Contoh pelaksanaan gotong royong yang merupakan wujud kerja sama di lingkungan sekolah adalah... (Latihan #29)",
      "opsi": {
        "A": "Menyontek saat ujian bersama-sama",
        "B": "Iuran memperbaiki jembatan desa",
        "C": "Salat jamaah di masjid komplek",
        "D": "Membersihkan kelas bersama regu piket",
        "E": "Memasak bersama keluarga di hari libur"
      },
      "kunci": "D",
      "pembahasan": "Lingkungan sekolah = kegiatan yang di area sekolah (pikét kelas, membersihkan taman baca, dll).",
      "trik": "Lihat konteks tempat: 'lingkungan sekolah' -> berkaitan dng kegiatan di sekolah."
    },
    {
      "id": "smp-7-ppkn-30",
      "teks": "Menolong korban bencana alam tanpa membedakan suku asalnya merupakan penerapan nilai Pancasila ke-... (Latihan #30)",
      "opsi": {
        "A": "SATU - Ketuhanan Yang Maha Esa",
        "B": "TIGA - Persatuan Indonesia",
        "C": "EMPAT - Kerakyatan yang Dipimpin... ",
        "D": "LIMA - Keadilan Sosial...",
        "E": "DUA - Kemanusiaan yang Adil dan Beradab"
      },
      "kunci": "E",
      "pembahasan": "Sikap saling peduli, menolong, menjunjung tinggi HAM, kemanusiaan masuk pada sila kedua (kemanusiaan yang beradab).",
      "trik": "Tolong-menolong/Donasi/Relawan = Sila 2."
    },
    {
      "id": "smp-7-ppkn-31",
      "teks": "Lembaga bentukan Jepang yang bertugas menyelidiki kesiapan kemerdekaan Indonesia adalah... (Latihan #31)",
      "opsi": {
        "A": "BPUPKI",
        "B": "PPKI",
        "C": "KNIP",
        "D": "DPR",
        "E": "MPR"
      },
      "kunci": "A",
      "pembahasan": "Jepang membentuk BPUPKI (Badan Penyelidik Usaha-usaha Persiapan Kemerdekaan Indonesia) atau Dokuritsu Junbi Cosakai untuk menyelidiki segala persiapan.",
      "trik": "Penyelidik = BPUPKI. Persiapan final = PPKI."
    },
    {
      "id": "smp-7-ppkn-32",
      "teks": "Tokoh yang mengusulkan rumusan dasar negara pada tanggal 1 Juni 1945 dan memberikan nama Pancasila adalah... (Latihan #32)",
      "opsi": {
        "A": "Bung Hatta",
        "B": "Ir. Soekarno",
        "C": "Muh. Yamin",
        "D": "Soepomo",
        "E": "A.A. Maramis"
      },
      "kunci": "B",
      "pembahasan": "Dalam sidang BPUPKI tanggal 1 Juni 1945, Ir. Soekarno menyampaikan usulan dasar negara dan memberinya nama Pancasila.",
      "trik": "Hari Lahir Pancasila (1 Juni) = Pidato Ir. Soekarno."
    },
    {
      "id": "smp-7-ppkn-33",
      "teks": "Panitia yang merumuskan Piagam Jakarta (Jakarta Charter) sebagai cikal bakal pembukaan UUD 1945 adalah... (Latihan #33)",
      "opsi": {
        "A": "Panitia Kecil",
        "B": "PPKI",
        "C": "Panitia Sembilan",
        "D": "BPUPKI",
        "E": "KNIP"
      },
      "kunci": "C",
      "pembahasan": "Panitia Sembilan yang dibentuk BPUPKI berhasil merumuskan naskah Mukadimah yang dikenal sebagai Piagam Jakarta pada 22 Juni 1945.",
      "trik": "Piagam Jakarta dihasilkan oleh 9 tokoh perumus (Panitia Sembilan)."
    },
    {
      "id": "smp-7-ppkn-34",
      "teks": "Aturan yang sumbernya berasal dari hati nurani manusia mengenai baik dan buruk suatu perbuatan disebut norma... (Latihan #34)",
      "opsi": {
        "A": "Agama",
        "B": "Kesopanan",
        "C": "Hukum",
        "D": "Kesusilaan",
        "E": "Adat"
      },
      "kunci": "D",
      "pembahasan": "Norma kesusilaan bersumber dari bisikan kalbu/hati nurani untuk menilai baik dan buruk (contoh: jujur, tidak menipu).",
      "trik": "Hati nurani = Kesusilaan."
    },
    {
      "id": "smp-7-ppkn-35",
      "teks": "Sanksi berupa pengucilan, dicemooh, atau tidak diikutsertakan dalam kegiatan masyarakat merupakan pelanggaran terhadap norma... (Latihan #35)",
      "opsi": {
        "A": "Hukum",
        "B": "Agama",
        "C": "Kesusilaan",
        "D": "Negara",
        "E": "Kesopanan dan adat"
      },
      "kunci": "E",
      "pembahasan": "Norma kesopanan (dan adat) adalah aturan pergaulan di masyarakat, sehingga pelanggarannya akan dikenai sanksi sosial seperti dikucilkan/dicemooh.",
      "trik": "Dihukum penjara = Hukum. Dosa = Agama. Dikucilkan = Kesopanan/Adat."
    },
    {
      "id": "smp-7-ppkn-36",
      "teks": "Sikap toleransi dalam kehidupan antarumat beragama di Indonesia bertujuan untuk... (Latihan #36)",
      "opsi": {
        "A": "Mewujudkan kerukunan dan kedamaian nasional",
        "B": "Mencapai satu ajaran agama",
        "C": "Menghindari hukuman pidana",
        "D": "Menyamakan keyakinan seluruh penduduk",
        "E": "Meningkatkan ibadah bersama antaragama"
      },
      "kunci": "A",
      "pembahasan": "Toleransi bertujuan menjalin kerukunan di tengah keragaman, menjaga kedamaian, bukan untuk menyamakan/menggabungkan keyakinan.",
      "trik": "Toleransi = rukun dengan saling membiarkan dan menghormati ibadah masing-masing."
    },
    {
      "id": "smp-7-ppkn-37",
      "teks": "Prinsip semboyan 'Bhinneka Tunggal Ika' bagi bangsa Indonesia adalah sebagai... (Latihan #37)",
      "opsi": {
        "A": "Alat perpecahan masyarakat",
        "B": "Pemersatu di tengah keberagaman suku, agama, dan budaya",
        "C": "Simbol dominasi mayoritas",
        "D": "Penanda bahwa Indonesia merupakan negara agama",
        "E": "Identitas bahwa suku tertentu lebih unggul"
      },
      "kunci": "B",
      "pembahasan": "Bhinneka Tunggal Ika artinya 'Berbeda-beda tetapi tetap satu jua', merupakan alat pemersatu bangsa yang majemuk.",
      "trik": "Bhinneka = Berbeda. Tunggal Ika = Satu Jua -> Pemersatu."
    },
    {
      "id": "smp-7-ppkn-38",
      "teks": "Sikap etnosentrisme dapat membahayakan NKRI karena... (Latihan #38)",
      "opsi": {
        "A": "Membuat kebudayaan luar mudah masuk",
        "B": "Memicu pertumbuhan ekonomi",
        "C": "Menganggap suku bangsa sendiri paling baik dan merendahkan suku lain",
        "D": "Dapat memperkuat dasar negara Pancasila",
        "E": "Menimbulkan sifat individualisme yang ekstrem"
      },
      "kunci": "C",
      "pembahasan": "Etnosentrisme adalah pandangan yang menganggap budayanya/sukunya lebih superior/baik daripada yang lain, sehingga memicu perpecahan.",
      "trik": "Etno = Suku/Budaya. Sentris = Berpusat (Merasa sukunya paling sentral/baik)."
    },
    {
      "id": "smp-7-ppkn-39",
      "teks": "Contoh pelaksanaan gotong royong yang merupakan wujud kerja sama di lingkungan sekolah adalah... (Latihan #39)",
      "opsi": {
        "A": "Menyontek saat ujian bersama-sama",
        "B": "Iuran memperbaiki jembatan desa",
        "C": "Salat jamaah di masjid komplek",
        "D": "Membersihkan kelas bersama regu piket",
        "E": "Memasak bersama keluarga di hari libur"
      },
      "kunci": "D",
      "pembahasan": "Lingkungan sekolah = kegiatan yang di area sekolah (pikét kelas, membersihkan taman baca, dll).",
      "trik": "Lihat konteks tempat: 'lingkungan sekolah' -> berkaitan dng kegiatan di sekolah."
    },
    {
      "id": "smp-7-ppkn-40",
      "teks": "Menolong korban bencana alam tanpa membedakan suku asalnya merupakan penerapan nilai Pancasila ke-... (Latihan #40)",
      "opsi": {
        "A": "SATU - Ketuhanan Yang Maha Esa",
        "B": "TIGA - Persatuan Indonesia",
        "C": "EMPAT - Kerakyatan yang Dipimpin... ",
        "D": "LIMA - Keadilan Sosial...",
        "E": "DUA - Kemanusiaan yang Adil dan Beradab"
      },
      "kunci": "E",
      "pembahasan": "Sikap saling peduli, menolong, menjunjung tinggi HAM, kemanusiaan masuk pada sila kedua (kemanusiaan yang beradab).",
      "trik": "Tolong-menolong/Donasi/Relawan = Sila 2."
    },
    {
      "id": "smp-7-ppkn-41",
      "teks": "Lembaga bentukan Jepang yang bertugas menyelidiki kesiapan kemerdekaan Indonesia adalah... (Latihan #41)",
      "opsi": {
        "A": "BPUPKI",
        "B": "PPKI",
        "C": "KNIP",
        "D": "DPR",
        "E": "MPR"
      },
      "kunci": "A",
      "pembahasan": "Jepang membentuk BPUPKI (Badan Penyelidik Usaha-usaha Persiapan Kemerdekaan Indonesia) atau Dokuritsu Junbi Cosakai untuk menyelidiki segala persiapan.",
      "trik": "Penyelidik = BPUPKI. Persiapan final = PPKI."
    },
    {
      "id": "smp-7-ppkn-42",
      "teks": "Tokoh yang mengusulkan rumusan dasar negara pada tanggal 1 Juni 1945 dan memberikan nama Pancasila adalah... (Latihan #42)",
      "opsi": {
        "A": "Bung Hatta",
        "B": "Ir. Soekarno",
        "C": "Muh. Yamin",
        "D": "Soepomo",
        "E": "A.A. Maramis"
      },
      "kunci": "B",
      "pembahasan": "Dalam sidang BPUPKI tanggal 1 Juni 1945, Ir. Soekarno menyampaikan usulan dasar negara dan memberinya nama Pancasila.",
      "trik": "Hari Lahir Pancasila (1 Juni) = Pidato Ir. Soekarno."
    },
    {
      "id": "smp-7-ppkn-43",
      "teks": "Panitia yang merumuskan Piagam Jakarta (Jakarta Charter) sebagai cikal bakal pembukaan UUD 1945 adalah... (Latihan #43)",
      "opsi": {
        "A": "Panitia Kecil",
        "B": "PPKI",
        "C": "Panitia Sembilan",
        "D": "BPUPKI",
        "E": "KNIP"
      },
      "kunci": "C",
      "pembahasan": "Panitia Sembilan yang dibentuk BPUPKI berhasil merumuskan naskah Mukadimah yang dikenal sebagai Piagam Jakarta pada 22 Juni 1945.",
      "trik": "Piagam Jakarta dihasilkan oleh 9 tokoh perumus (Panitia Sembilan)."
    },
    {
      "id": "smp-7-ppkn-44",
      "teks": "Aturan yang sumbernya berasal dari hati nurani manusia mengenai baik dan buruk suatu perbuatan disebut norma... (Latihan #44)",
      "opsi": {
        "A": "Agama",
        "B": "Kesopanan",
        "C": "Hukum",
        "D": "Kesusilaan",
        "E": "Adat"
      },
      "kunci": "D",
      "pembahasan": "Norma kesusilaan bersumber dari bisikan kalbu/hati nurani untuk menilai baik dan buruk (contoh: jujur, tidak menipu).",
      "trik": "Hati nurani = Kesusilaan."
    },
    {
      "id": "smp-7-ppkn-45",
      "teks": "Sanksi berupa pengucilan, dicemooh, atau tidak diikutsertakan dalam kegiatan masyarakat merupakan pelanggaran terhadap norma... (Latihan #45)",
      "opsi": {
        "A": "Hukum",
        "B": "Agama",
        "C": "Kesusilaan",
        "D": "Negara",
        "E": "Kesopanan dan adat"
      },
      "kunci": "E",
      "pembahasan": "Norma kesopanan (dan adat) adalah aturan pergaulan di masyarakat, sehingga pelanggarannya akan dikenai sanksi sosial seperti dikucilkan/dicemooh.",
      "trik": "Dihukum penjara = Hukum. Dosa = Agama. Dikucilkan = Kesopanan/Adat."
    },
    {
      "id": "smp-7-ppkn-46",
      "teks": "Sikap toleransi dalam kehidupan antarumat beragama di Indonesia bertujuan untuk... (Latihan #46)",
      "opsi": {
        "A": "Mewujudkan kerukunan dan kedamaian nasional",
        "B": "Mencapai satu ajaran agama",
        "C": "Menghindari hukuman pidana",
        "D": "Menyamakan keyakinan seluruh penduduk",
        "E": "Meningkatkan ibadah bersama antaragama"
      },
      "kunci": "A",
      "pembahasan": "Toleransi bertujuan menjalin kerukunan di tengah keragaman, menjaga kedamaian, bukan untuk menyamakan/menggabungkan keyakinan.",
      "trik": "Toleransi = rukun dengan saling membiarkan dan menghormati ibadah masing-masing."
    },
    {
      "id": "smp-7-ppkn-47",
      "teks": "Prinsip semboyan 'Bhinneka Tunggal Ika' bagi bangsa Indonesia adalah sebagai... (Latihan #47)",
      "opsi": {
        "A": "Alat perpecahan masyarakat",
        "B": "Pemersatu di tengah keberagaman suku, agama, dan budaya",
        "C": "Simbol dominasi mayoritas",
        "D": "Penanda bahwa Indonesia merupakan negara agama",
        "E": "Identitas bahwa suku tertentu lebih unggul"
      },
      "kunci": "B",
      "pembahasan": "Bhinneka Tunggal Ika artinya 'Berbeda-beda tetapi tetap satu jua', merupakan alat pemersatu bangsa yang majemuk.",
      "trik": "Bhinneka = Berbeda. Tunggal Ika = Satu Jua -> Pemersatu."
    },
    {
      "id": "smp-7-ppkn-48",
      "teks": "Sikap etnosentrisme dapat membahayakan NKRI karena... (Latihan #48)",
      "opsi": {
        "A": "Membuat kebudayaan luar mudah masuk",
        "B": "Memicu pertumbuhan ekonomi",
        "C": "Menganggap suku bangsa sendiri paling baik dan merendahkan suku lain",
        "D": "Dapat memperkuat dasar negara Pancasila",
        "E": "Menimbulkan sifat individualisme yang ekstrem"
      },
      "kunci": "C",
      "pembahasan": "Etnosentrisme adalah pandangan yang menganggap budayanya/sukunya lebih superior/baik daripada yang lain, sehingga memicu perpecahan.",
      "trik": "Etno = Suku/Budaya. Sentris = Berpusat (Merasa sukunya paling sentral/baik)."
    },
    {
      "id": "smp-7-ppkn-49",
      "teks": "Contoh pelaksanaan gotong royong yang merupakan wujud kerja sama di lingkungan sekolah adalah... (Latihan #49)",
      "opsi": {
        "A": "Menyontek saat ujian bersama-sama",
        "B": "Iuran memperbaiki jembatan desa",
        "C": "Salat jamaah di masjid komplek",
        "D": "Membersihkan kelas bersama regu piket",
        "E": "Memasak bersama keluarga di hari libur"
      },
      "kunci": "D",
      "pembahasan": "Lingkungan sekolah = kegiatan yang di area sekolah (pikét kelas, membersihkan taman baca, dll).",
      "trik": "Lihat konteks tempat: 'lingkungan sekolah' -> berkaitan dng kegiatan di sekolah."
    },
    {
      "id": "smp-7-ppkn-50",
      "teks": "Menolong korban bencana alam tanpa membedakan suku asalnya merupakan penerapan nilai Pancasila ke-... (Latihan #50)",
      "opsi": {
        "A": "SATU - Ketuhanan Yang Maha Esa",
        "B": "TIGA - Persatuan Indonesia",
        "C": "EMPAT - Kerakyatan yang Dipimpin... ",
        "D": "LIMA - Keadilan Sosial...",
        "E": "DUA - Kemanusiaan yang Adil dan Beradab"
      },
      "kunci": "E",
      "pembahasan": "Sikap saling peduli, menolong, menjunjung tinggi HAM, kemanusiaan masuk pada sila kedua (kemanusiaan yang beradab).",
      "trik": "Tolong-menolong/Donasi/Relawan = Sila 2."
    }
  ]
}